[
  {
    "nama": "Puskesmas Sidoarjo",
    "jenis": "puskesmas",
    "kontak": "(031) 8921956",
    "alamat": "Jalan Dr. Soetomo No.14, Gajah Timur, Magersari, Kec. Sidoarjo, Kabupaten Sidoarjo, Jawa Timur 61212",
    "sosialmedia": "Belum Tersedia"
  },
  {
    "nama": "Puskesmas Candi",
    "jenis": "puskesmas",
    "kontak": "(031) 8963973",
    "alamat": "Jalan Moh Ridwan No.5, Gelam, Kec. Candi, Kabupaten Sidoarjo, Jawa Timur 61271",
    "sosialmedia": "Belum Tersedia"
  },
  {
    "nama": "Puskesmas Balongbendo",
    "jenis": "puskesmas",
    "kontak": "(031) 8976521",
    "alamat": "Jalan Mayjen Bambang Yuwono No.11, Seduri, Kec. BalongBendo, Kabupaten Sidoarjo, Jawa Timur 61263",
    "sosialmedia": "Belum Tersedia"
  },
  {
    "nama": "Puskesmas Buduran",
    "jenis": "puskesmas",
    "kontak": "(031) 8967494",
    "alamat": "Jalan Jawa No.2, Banarmelati, Wadungasih, Kec. Buduran, Kabupaten Sidoarjo, Jawa Timur 61252",
    "sosialmedia": "Belum Tersedia"
  },
  {
    "nama": "Puskesmas Tarik",
    "jenis": "puskesmas",
    "kontak": "(031) 8976915",
    "alamat": "Jalan Raya Tarik, Kemuning, Kec. Tarik, Kabupaten Sidoarjo, Jawa Timur 61265",
    "sosialmedia": "Belum Tersedia"
  },
  {
    "nama": "Puskesmas Sekardangan",
    "jenis": "puskesmas",
    "kontak": "(031) 8962125",
    "alamat": "Jalan Wijaya Kusuma No.4, Plipir, Sekardangan, Kec. Sidoarjo, Kabupaten Sidoarjo, Jawa Timur 61215",
    "sosialmedia": "Belum Tersedia"
  },
  {
    "nama": "Puskesmas Urangagung",
    "jenis": "puskesmas",
    "kontak": "(031) 8950177",
    "alamat": "Jalan Raya Cemeng Kalang No.15, Cemengkalang, Cemeng Kalang, Kec. Sidoarjo, Kabupaten Sidoarjo, Jawa Timur 61234",
    "sosialmedia": "Belum Tersedia"
  },
  {
    "nama": "Puskesmas Waru",
    "jenis": "puskesmas",
    "kontak": "(031) 8676643",
    "alamat": "Jalan Barito Blok EH No.1, Jalan Raya Wisma Tropodo, Tropodo Kulon, Tropodo, Kec. Waru, Kabupaten Sidoarjo, Jawa Timur 61256",
    "sosialmedia": "Belum Tersedia"
  },
  {
    "nama": "Puskesmas Tulangan",
    "jenis": "puskesmas",
    "kontak": "(031) 8850743",
    "alamat": "Jalan Raya Kemantren, Kemantren, Tulangan, Kec. Tulangan, Kabupaten Sidoarjo, Jawa Timur 61273",
    "sosialmedia": "Belum Tersedia"
  },
  {
    "nama": "Puskesmas Krembung",
    "jenis": "puskesmas",
    "kontak": "(031) 8851542",
    "alamat": "Jalan Raya Krembung No.18, Krembung Timur, Krembung, Sidoarjo, Kabupaten Sidoarjo, Jawa Timur 61275",
    "sosialmedia": "Belum Tersedia"
  },
  {
    "nama": "Puskesmas Sedati",
    "jenis": "puskesmas",
    "kontak": "(031) 8917452",
    "alamat": "Jalan Senopati No.3-7, Kepuh, Betro, Kec. Sedati, Kabupaten Sidoarjo, Jawa Timur 61253",
    "sosialmedia": "Belum Tersedia"
  },
  {
    "nama": "Puskesmas Medaeng",
    "jenis": "puskesmas",
    "kontak": "Belum Tersedia",
    "alamat": "Jalan Joyoboyo No.49 A, Bungur, Medaeng, Kec. Waru, Kabupaten Sidoarjo, Jawa Timur 61256",
    "sosialmedia": "Belum Tersedia"
  },
  {
    "nama": "Puskesmas Prambon",
    "jenis": "puskesmas",
    "kontak": "(031) 8974735",
    "alamat": "Jalan Raya Prambon No.125, Prambon, Kec. Prambon, Kabupaten Sidoarjo, Jawa Timur 61264",
    "sosialmedia": "Belum Tersedia"
  },
  {
    "nama": "Puskesmas Wonoayu",
    "jenis": "puskesmas",
    "kontak": "(031) 8976920",
    "alamat": "Jalan Raya Wonoayu, Popoh, Jimbaran Kulon, Kec. Wonoayu, Kabupaten Sidoarjo, Jawa Timur 61261",
    "sosialmedia": "Belum Tersedia"
  },
  {
    "nama": "Puskesmas Trosobo",
    "jenis": "puskesmas",
    "kontak": "(031) 7873664",
    "alamat": "Jalan Raya Trosobo, Sabowidoro, Trosobo, Kec. Taman, Kabupaten Sidoarjo, Jawa Timur 61257",
    "sosialmedia": "Belum Tersedia"
  },
  {
    "nama": "Puskesmas Taman",
    "jenis": "puskesmas",
    "kontak": "(031) 7881201",
    "alamat": "Jalan Raya Ngelom No.50, Ngelom, Kec. Taman, Kabupaten Sidoarjo, Jawa Timur 61257",
    "sosialmedia": "Belum Tersedia"
  },
  {
    "nama": "Puskesmas Tanggulangin",
    "jenis": "puskesmas",
    "kontak": "(031) 8967232",
    "alamat": "Jalan Putat No.36, Putat Selatan, Putat, Kec. Tanggulangin, Kabupaten Sidoarjo, Jawa Timur 61272",
    "sosialmedia": "Belum Tersedia"
  },
  {
    "nama": "Puskesmas Krian",
    "jenis": "puskesmas",
    "kontak": "(031) 8971244",
    "alamat": "Jalan Setiabudi C No.5, Krian, Kec. Krian, Kabupaten Sidoarjo, Jawa Timur 61262",
    "sosialmedia": "Belum Tersedia"
  },
  {
    "nama": "Puskesmas Sukodono",
    "jenis": "puskesmas",
    "kontak": "(031) 8831727",
    "alamat": "Jalan Raya Bukit Kweni, Anggaswangi, Kec. Sukodono, Kabupaten Sidoarjo, Jawa Timur 61258",
    "sosialmedia": "Belum Tersedia"
  },
  {
    "nama": "Puskesmas Jabon",
    "jenis": "puskesmas",
    "kontak": "(0343) 855690",
    "alamat": "Jalan Majapahit No.2, Dukuhsari II, Dukuhsari, Kec. Jabon, Kabupaten Sidoarjo, Jawa Timur 61276",
    "sosialmedia": "Belum Tersedia"
  },
  {
    "nama": "Puskesmas Ganting",
    "jenis": "puskesmas",
    "kontak": "Belum Tersedia",
    "alamat": "Jalan Singo Menggolo No.1, Dusun Malang Ganting, Ganting, Kec. Gedangan, Kabupaten Sidoarjo, Jawa Timur 61254",
    "sosialmedia": "Belum Tersedia"
  },
  {
    "nama": "Puskesmas Gedangan",
    "jenis": "puskesmas",
    "kontak": "(031) 8533726",
    "alamat": "Jalan Raya Gedangan No.330 Gedangan Sidoarjo, Megersari, Gedangan, Kec. Gedangan, Kabupaten Sidoarjo, Jawa Timur 61254",
    "sosialmedia": "Belum Tersedia"
  },
  {
    "nama": "Puskesmas Barengkrajan",
    "jenis": "puskesmas",
    "kontak": "Belum Tersedia",
    "alamat": "Jalan Barengkrajan, Sidorono, Sidorejo, Kec. Krian, Kabupaten Sidoarjo, Jawa Timur 61262",
    "sosialmedia": "Belum Tersedia"
  },
  {
    "nama": "Puskesmas Porong",
    "jenis": "puskesmas",
    "kontak": "(0343) 852031",
    "alamat": "Jalan Juwet Utara No. 265, Porong, Juwet, Juwetkenongo, Sidoarjo, Kabupaten Sidoarjo, Jawa Timur 67155",
    "sosialmedia": "Belum Tersedia"
  },
  {
    "nama": "Puskesmas Kepadangan",
    "jenis": "puskesmas",
    "kontak": "(031) 8854215",
    "alamat": "Jalan Raya Kepadangan No.100, Kepadangan, Kec. Tulangan, Kabupaten Sidoarjo, Jawa Timur 61273",
    "sosialmedia": "Belum Tersedia"
  },
  {
    "nama": "Puskesmas Kedungsolo",
    "jenis": "puskesmas",
    "kontak": "(0343) 853089",
    "alamat": "Jalan Kedungsolo No.1, Kedungkampil, Kedungsolo, Kec. Porong, Kabupaten Sidoarjo, Jawa Timur 61274",
    "sosialmedia": "Belum Tersedia"
  }
]